Metadata-Version: 1.2
Name: pyplotjuggler
Version: 0.1.5
Summary: A timeseries visualization tool in Python
Home-page: https://github.com/AtsushiSakai/pyplotjuggler
Author: Atsushi Sakai
Author-email: asakaig@gmail.com
Maintainer: Atsushi Sakai
Maintainer-email: asakaig@gmail.com
License: MIT
Keywords: python matplotlib tkinter
Platform: UNKNOWN
Classifier: Programming Language :: Python :: 3
Classifier: License :: OSI Approved :: MIT License
Classifier: Topic :: Scientific/Engineering :: Visualization
Requires-Python: >3.6.0
